suncal/__init__.py
suncal/__main__.py
suncal/version.py
suncal/common/__init__.py
suncal/common/distributions.py
suncal/common/matrix.py
suncal/common/multivariate_t.py
suncal/common/plotting.py
suncal/common/report.py
suncal/common/reporter.py
suncal/common/ttable.py
suncal/common/unitmgr.py
suncal/common/uparser.py
suncal/common/style/__init__.py
suncal/common/style/css.py
suncal/common/style/latexchars.py
suncal/common/style/suncal_dark.mplstyle
suncal/common/style/suncal_light.mplstyle
suncal/curvefit/__init__.py
suncal/curvefit/curvefit.py
suncal/curvefit/curvefit_model.py
suncal/curvefit/fitparse.py
suncal/curvefit/uncertarray.py
suncal/curvefit/report/__init__.py
suncal/curvefit/report/curvefit.py
suncal/curvefit/results/__init__.py
suncal/curvefit/results/curvefit.py
suncal/datasets/__init__.py
suncal/datasets/dataset.py
suncal/datasets/dataset_model.py
suncal/datasets/report/__init__.py
suncal/datasets/report/dataset.py
suncal/distexplore/__init__.py
suncal/distexplore/dist_explore.py
suncal/distexplore/report/__init__.py
suncal/distexplore/report/dist_explore.py
suncal/gui/SUNCALmanual.pdf
suncal/gui/__init__.py
suncal/gui/__main__.py
suncal/gui/gen_licenses.py
suncal/gui/gui_common.py
suncal/gui/gui_main.py
suncal/gui/gui_math.py
suncal/gui/gui_settings.py
suncal/gui/gui_styles.py
suncal/gui/licenses.py
suncal/gui/page_about.py
suncal/gui/page_csvload.py
suncal/gui/page_curvefit.py
suncal/gui/page_dataimport.py
suncal/gui/page_dataset.py
suncal/gui/page_distexplore.py
suncal/gui/page_guardband.py
suncal/gui/page_interval.py
suncal/gui/page_reverse.py
suncal/gui/page_risk.py
suncal/gui/page_settings.py
suncal/gui/page_sweep.py
suncal/gui/page_typea.py
suncal/gui/page_uncert.py
suncal/gui/page_uncert_input.py
suncal/gui/page_uncert_output.py
suncal/gui/page_wizard.py
suncal/gui/tool_risk.py
suncal/gui/tool_riskcurves.py
suncal/gui/tool_ttable.py
suncal/gui/tool_units.py
suncal/gui/help_strings/__init__.py
suncal/gui/help_strings/anova_help.py
suncal-1.6.5.dist-info/LICENSE
suncal-1.6.5.dist-info/METADATA
suncal-1.6.5.dist-info/WHEEL
suncal-1.6.5.dist-info/entry_points.txt
suncal-1.6.5.dist-info/top_level.txt
suncal-1.6.5.dist-info/zip-safe
suncal-1.6.5.dist-info/RECORD
