Metadata-Version: 2.1
Name: suncal
Version: 1.6.5
Summary: Sandia PSL Uncertainty Calculator
Home-page: https://sandiapsl.github.io
Author: Collin J. Delker
Author-email: uncertainty@sandia.gov
License: GNU General Public License v3 (GPLv3)
Project-URL: Documentation, https://sandiapsl.github.io
Project-URL: Source Code, https://github.com/SandiaPSL/UncertaintyCalc
Keywords: uncertainty,metrology,measurement,GUM
Classifier: Development Status :: 4 - Beta
Classifier: Programming Language :: Python :: 3
Classifier: Programming Language :: Python :: 3.9
Classifier: Programming Language :: Python :: 3.10
Classifier: Programming Language :: Python :: 3.11
Classifier: Programming Language :: Python :: 3.12
Classifier: License :: OSI Approved :: GNU General Public License v3 (GPLv3)
Classifier: Operating System :: OS Independent
Classifier: Intended Audience :: Education
Classifier: Intended Audience :: Science/Research
Classifier: Intended Audience :: End Users/Desktop
Requires-Python: >=3.9
License-File: LICENSE
Requires-Dist: numpy >=1.22
Requires-Dist: matplotlib >=3.3
Requires-Dist: scipy >=1.9
Requires-Dist: sympy >=1.11.1
Requires-Dist: pint >=0.22
Requires-Dist: markdown >=3.3
Requires-Dist: pyyaml >=5.4
Provides-Extra: gui
Requires-Dist: pyqt6 ; extra == 'gui'
